Metadata-Version: 2.1
Name: anishmd
Version: 0.0.1
Summary: anishmd
Home-page: UNKNOWN
Author: Anish Agrawal
Author-email: your.email@example.com
License: UNKNOWN
Platform: UNKNOWN
